custom/build.py
venv/bin/activate_this.py
protobuf_custom_build-0.2.0.dist-info/LICENSE
protobuf_custom_build-0.2.0.dist-info/METADATA
protobuf_custom_build-0.2.0.dist-info/WHEEL
protobuf_custom_build-0.2.0.dist-info/entry_points.txt
protobuf_custom_build-0.2.0.dist-info/top_level.txt
protobuf_custom_build-0.2.0.dist-info/RECORD
