Metadata-Version: 2.1
Name: protobuf-custom-build
Version: 0.2.0
Summary: Custom build step for protobuf packages
Home-page: https://github.com/sbrother/protobuf-custom-build
Author: Sam Brotherton
Author-email: sam@cairnlabs.com
License: UNKNOWN
Platform: UNKNOWN
Classifier: Programming Language :: Python :: 3
Classifier: License :: OSI Approved :: MIT License
License-File: LICENSE
